{
    "relationships": [
        {
            "relationshipName": "pacientes",
            "otherEntityName": "pacientes",
            "relationshipType": "many-to-one",
            "otherEntityField": "nome"
        }
    ],
    "fields": [
        {
            "fieldName": "dataMedicacao",
            "fieldType": "LocalDate",
            "fieldValidateRules": [
                "required"
            ]
        },
        {
            "fieldName": "valor",
            "fieldType": "String",
            "fieldValidateRules": [
                "required"
            ]
        },
        {
            "fieldName": "verificar",
            "fieldType": "Verificacoes",
            "fieldValues": "PA,HGT,TAX,FC",
            "fieldValidateRules": [
                "required"
            ]
        },
        {
            "fieldName": "horario",
            "fieldType": "Horas",
            "fieldValues": "H12,H24,H18,H6",
            "fieldValidateRules": [
                "required"
            ]
        }
    ],
    "changelogDate": "20160516034618",
    "dto": "no",
    "service": "no",
    "entityTableName": "medicacao",
    "pagination": "infinite-scroll"
}
