{
  "name": "Prescricoes",
  "fields": [
    {
      "fieldName": "prescricao",
      "fieldType": "String",
      "fieldValidateRules": ["required", "maxlength"],
      "fieldValidateRulesMaxlength": "100"
    }
  ],
  "relationships": [
    {
      "relationshipType": "one-to-many",
      "otherEntityName": "internacoesDetalhes",
      "otherEntityRelationshipName": "prescricoes",
      "relationshipName": "internacoesDetalhes"
    }
  ],
  "entityTableName": "prescricoes",
  "dto": "no",
  "pagination": "no",
  "service": "no",
  "jpaMetamodelFiltering": false,
  "fluentMethods": true,
  "readOnly": false,
  "embedded": false,
  "applications": "*",
  "changelogDate": "20210927223239"
}
